hapless/__init__.py
hapless/cli.py
hapless/cli_utils.py
hapless/config.py
hapless/formatters.py
hapless/hap.py
hapless/main.py
hapless/ui.py
hapless/utils.py
hapless-0.15.1.dist-info/METADATA
hapless-0.15.1.dist-info/WHEEL
hapless-0.15.1.dist-info/entry_points.txt
hapless-0.15.1.dist-info/RECORD
