Metadata-Version: 2.1
Name: hapless
Version: 0.15.1
Summary: Run and track processes in background
Home-page: https://github.com/bmwant/hapless
License: MIT
Keywords: cli,job,runner,background,process
Author: Misha Behersky
Author-email: bmwant@gmail.com
Requires-Python: >=3.8,<4.0
Classifier: Development Status :: 4 - Beta
Classifier: Environment :: Console
Classifier: Intended Audience :: Developers
Classifier: License :: OSI Approved :: MIT License
Classifier: Operating System :: Unix
Classifier: Programming Language :: Python :: 3
Classifier: Programming Language :: Python :: 3.8
Classifier: Programming Language :: Python :: 3.9
Classifier: Programming Language :: Python :: 3.10
Classifier: Programming Language :: Python :: 3.11
Classifier: Programming Language :: Python :: 3.12
Classifier: Programming Language :: Python :: 3.13
Classifier: Programming Language :: Python :: 3 :: Only
Classifier: Programming Language :: Python :: 3.14
Classifier: Programming Language :: Unix Shell
Classifier: Topic :: System
Classifier: Topic :: Utilities
Provides-Extra: dev
Requires-Dist: click (>=8.1.2,<9.0.0)
Requires-Dist: django-environ (>=0.11.2,<0.12.0) ; python_version < "3.9"
Requires-Dist: django-environ (>=0.12.0,<0.13.0) ; python_version >= "3.9"
Requires-Dist: humanize (>=4.1.0,<5.0.0)
Requires-Dist: nox (>=2024.10.9,<2025.0.0) ; extra == "dev"
Requires-Dist: psutil (>=6.1.0,<7.0.0)
Requires-Dist: pytest (>=7.4.4,<8.0.0) ; extra == "dev"
Requires-Dist: pytest-cov (>=3.0.0,<4.0.0) ; extra == "dev"
Requires-Dist: pytest-env (>=1.1.2,<2.0.0) ; extra == "dev"
Requires-Dist: rich (>=13.5.2,<14.0.0)
Requires-Dist: ruff (>=0.9.0,<0.10.0) ; extra == "dev"
Requires-Dist: structlog (>=25.4.0,<26.0.0)
Requires-Dist: ty (>=0.0.1a21,<0.0.2) ; extra == "dev"
Requires-Dist: typing-extensions (>=4.13.2,<5.0.0) ; python_version < "3.10"
Project-URL: Blog post, https://bmwant.link/hapless-easily-run-and-manage-background-processes/
Project-URL: Repository, https://github.com/bmwant/hapless
